{"v":"4.8.0","meta":{"g":"LottieFiles AE 3.3.6","a":"","k":"","d":"","tc":"#FFD600"},"fr":60,"ip":38,"op":184,"w":600,"h":400,"nm":"Ochre_Logo_R2_V3","ddd":0,"assets":[],"layers":[{"ddd":0,"ind":1,"ty":4,"nm":"Shape Layer 5","td":1,"sr":1,"ks":{"o":{"a":0,"k":100,"ix":11},"r":{"a":0,"k":0,"ix":10},"p":{"a":0,"k":[300,193,0],"ix":2},"a":{"a":0,"k":[0,0,0],"ix":1},"s":{"a":0,"k":[100,100,100],"ix":6}},"ao":0,"shapes":[{"ty":"gr","it":[{"ind":0,"ty":"sh","ix":1,"ks":{"a":0,"k":{"i":[[0,0],[0,0]],"o":[[0,0],[0,0]],"v":[[-238,150],[246,152]],"c":false},"ix":2},"nm":"Path 1","mn":"ADBE Vector Shape - Group","hd":false},{"ty":"st","c":{"a":0,"k":[0,0,0,1],"ix":3},"o":{"a":0,"k":100,"ix":4},"w":{"a":0,"k":45,"ix":5},"lc":1,"lj":1,"ml":4,"bm":0,"nm":"Stroke 1","mn":"ADBE Vector Graphic - Stroke","hd":false},{"ty":"fl","c":{"a":0,"k":[0.266666666667,0.266666666667,0.266666666667,1],"ix":4},"o":{"a":0,"k":100,"ix":5},"r":1,"bm":0,"nm":"Fill 1","mn":"ADBE Vector Graphic - Fill","hd":false},{"ty":"tr","p":{"a":0,"k":[0,0],"ix":2},"a":{"a":0,"k":[0,0],"ix":1},"s":{"a":0,"k":[100,100],"ix":3},"r":{"a":0,"k":0,"ix":6},"o":{"a":0,"k":100,"ix":7},"sk":{"a":0,"k":0,"ix":4},"sa":{"a":0,"k":0,"ix":5},"nm":"Transform"}],"nm":"Shape 1","np":3,"cix":2,"bm":0,"ix":1,"mn":"ADBE Vector Group","hd":false},{"ty":"tm","s":{"a":0,"k":0,"ix":1},"e":{"a":1,"k":[{"i":{"x":[0.833],"y":[0.833]},"o":{"x":[0.167],"y":[0.167]},"t":108.107,"s":[0]},{"t":140.140625,"s":[100]}],"ix":2},"o":{"a":0,"k":0,"ix":3},"m":1,"ix":2,"nm":"Trim Paths 1","mn":"ADBE Vector Filter - Trim","hd":false}],"ip":0,"op":1801.8018018018,"st":0,"bm":0},{"ddd":0,"ind":2,"ty":4,"nm":"On Your Conditions Outlines","tt":1,"sr":1,"ks":{"o":{"a":1,"k":[{"i":{"x":[0.833],"y":[0.833]},"o":{"x":[0.167],"y":[0.167]},"t":108,"s":[0]},{"i":{"x":[0.833],"y":[0.833]},"o":{"x":[0.167],"y":[0.167]},"t":164.057,"s":[76.857]},{"t":172.064453125,"s":[100]}],"ix":11},"r":{"a":0,"k":0,"ix":10},"p":{"a":0,"k":[312.5,361.5,0],"ix":2},"a":{"a":0,"k":[0,0,0],"ix":1},"s":{"a":0,"k":[100,100,100],"ix":6}},"ao":0,"shapes":[{"ty":"gr","it":[{"ind":0,"ty":"sh","ix":1,"ks":{"a":0,"k":{"i":[[-1.65,0.705],[-1.155,1.365],[-0.63,2.025],[0,2.64],[0.63,2.01],[1.155,1.38],[1.65,0.705],[2.01,0],[1.635,-0.705],[1.155,-1.38],[0.63,-2.01],[0,-2.64],[-0.63,-2.025],[-1.155,-1.365],[-1.635,-0.705],[-2.04,0]],"o":[[1.65,-0.705],[1.155,-1.365],[0.63,-2.025],[0,-2.64],[-0.63,-2.01],[-1.155,-1.38],[-1.65,-0.705],[-2.04,0],[-1.635,0.705],[-1.155,1.38],[-0.63,2.01],[0,2.64],[0.63,2.025],[1.155,1.365],[1.635,0.705],[2.01,0]],"v":[[-221.08,-4.718],[-216.872,-7.823],[-214.195,-12.908],[-213.25,-19.905],[-214.195,-26.88],[-216.872,-31.965],[-221.08,-35.093],[-226.57,-36.15],[-232.083,-35.093],[-236.268,-31.965],[-238.945,-26.88],[-239.89,-19.905],[-238.945,-12.908],[-236.268,-7.823],[-232.083,-4.718],[-226.57,-3.66]],"c":true},"ix":2},"nm":"O","mn":"ADBE Vector Shape - Group","hd":false},{"ind":1,"ty":"sh","ix":2,"ks":{"a":0,"k":{"i":[[1.14,0.482],[0.825,0.904],[0.45,1.264],[0,1.566],[0,0],[-0.45,1.264],[-0.825,0.904],[-1.14,0.482],[-1.35,0],[-1.14,-0.482],[-0.825,-0.903],[-0.45,-1.264],[0,-1.565],[0,0],[0.45,-1.264],[0.825,-0.903],[1.14,-0.482],[1.35,0]],"o":[[-1.14,-0.482],[-0.825,-0.903],[-0.45,-1.264],[0,0],[0,-1.565],[0.45,-1.264],[0.825,-0.903],[1.14,-0.482],[1.35,0],[1.14,0.482],[0.825,0.904],[0.45,1.264],[0,0],[0,1.566],[-0.45,1.264],[-0.825,0.904],[-1.14,0.482],[-1.35,0]],"v":[[-230.305,-7.713],[-233.253,-9.79],[-235.165,-13.042],[-235.84,-17.286],[-235.84,-22.525],[-235.165,-26.769],[-233.253,-30.021],[-230.305,-32.098],[-226.57,-32.82],[-222.835,-32.098],[-219.887,-30.021],[-217.975,-26.769],[-217.3,-22.525],[-217.3,-17.286],[-217.975,-13.042],[-219.887,-9.79],[-222.835,-7.713],[-226.57,-6.99]],"c":true},"ix":2},"nm":"O","mn":"ADBE Vector Shape - Group","hd":false},{"ty":"fl","c":{"a":0,"k":[0.152941176471,0.152941176471,0.152941176471,1],"ix":4},"o":{"a":0,"k":100,"ix":5},"r":1,"bm":0,"nm":"Fill 1","mn":"ADBE Vector Graphic - Fill","hd":false},{"ty":"tr","p":{"a":0,"k":[0,0],"ix":2},"a":{"a":0,"k":[0,0],"ix":1},"s":{"a":0,"k":[100,100],"ix":3},"r":{"a":0,"k":0,"ix":6},"o":{"a":0,"k":100,"ix":7},"sk":{"a":0,"k":0,"ix":4},"sa":{"a":0,"k":0,"ix":5},"nm":"Transform"}],"nm":"O","np":5,"cix":2,"bm":0,"ix":1,"mn":"ADBE Vector Group","hd":false},{"ty":"gr","it":[{"ind":0,"ty":"sh","ix":1,"ks":{"a":0,"k":{"i":[[0,0],[0,0],[-0.315,0.556],[-0.54,0.361],[-0.675,0.181],[-0.72,0],[0,-4.179],[0,0],[0,0],[0,0],[1.395,1.545],[2.4,0],[1.035,-0.772],[0.57,-1.306],[0,0],[0,0],[0,0],[0,0]],"o":[[0,0],[0,-0.752],[0.315,-0.556],[0.54,-0.361],[0.675,-0.18],[3.51,0],[0,0],[0,0],[0,0],[0,-2.82],[-1.395,-1.545],[-1.74,0],[-1.035,0.772],[0,0],[0,0],[0,0],[0,0],[0,0]],"v":[[-198.085,-4.2],[-198.085,-20.346],[-197.612,-22.307],[-196.33,-23.683],[-194.507,-24.495],[-192.415,-24.765],[-187.15,-18.496],[-187.15,-4.2],[-183.55,-4.2],[-183.55,-19.095],[-185.642,-25.643],[-191.335,-27.96],[-195.497,-26.802],[-197.905,-23.683],[-198.085,-23.683],[-198.085,-27.42],[-201.685,-27.42],[-201.685,-4.2]],"c":true},"ix":2},"nm":"n","mn":"ADBE Vector Shape - Group","hd":false},{"ty":"fl","c":{"a":0,"k":[0.152941176471,0.152941176471,0.152941176471,1],"ix":4},"o":{"a":0,"k":100,"ix":5},"r":1,"bm":0,"nm":"Fill 1","mn":"ADBE Vector Graphic - Fill","hd":false},{"ty":"tr","p":{"a":0,"k":[0,0],"ix":2},"a":{"a":0,"k":[0,0],"ix":1},"s":{"a":0,"k":[100,100],"ix":3},"r":{"a":0,"k":0,"ix":6},"o":{"a":0,"k":100,"ix":7},"sk":{"a":0,"k":0,"ix":4},"sa":{"a":0,"k":0,"ix":5},"nm":"Transform"}],"nm":"n","np":3,"cix":2,"bm":0,"ix":2,"mn":"ADBE Vector Group","hd":false},{"ty":"gr","it":[{"ind":0,"ty":"sh","ix":1,"ks":{"a":0,"k":{"i":[[0,0],[0,0],[0,0],[0,0],[0,0],[0,0],[0,0],[0,0],[0,0],[0,0]],"o":[[0,0],[0,0],[0,0],[0,0],[0,0],[0,0],[0,0],[0,0],[0,0],[0,0]],"v":[[-143.905,-4.2],[-143.905,-16.755],[-132.97,-35.61],[-137.29,-35.61],[-145.66,-20.49],[-145.795,-20.49],[-154.165,-35.61],[-158.485,-35.61],[-147.685,-16.62],[-147.685,-4.2]],"c":true},"ix":2},"nm":"Y","mn":"ADBE Vector Shape - Group","hd":false},{"ty":"fl","c":{"a":0,"k":[0.152941176471,0.152941176471,0.152941176471,1],"ix":4},"o":{"a":0,"k":100,"ix":5},"r":1,"bm":0,"nm":"Fill 1","mn":"ADBE Vector Graphic - Fill","hd":false},{"ty":"tr","p":{"a":0,"k":[0,0],"ix":2},"a":{"a":0,"k":[0,0],"ix":1},"s":{"a":0,"k":[100,100],"ix":3},"r":{"a":0,"k":0,"ix":6},"o":{"a":0,"k":100,"ix":7},"sk":{"a":0,"k":0,"ix":4},"sa":{"a":0,"k":0,"ix":5},"nm":"Transform"}],"nm":"Y","np":3,"cix":2,"bm":0,"ix":3,"mn":"ADBE Vector Group","hd":false},{"ty":"gr","it":[{"ind":0,"ty":"sh","ix":1,"ks":{"a":0,"k":{"i":[[-1.275,0.57],[-0.93,1.065],[-0.51,1.485],[0,1.86],[0.51,1.5],[0.93,1.065],[1.275,0.57],[1.56,0],[1.29,-0.57],[0.915,-1.065],[0.51,-1.5],[0,-1.83],[-0.51,-1.485],[-0.915,-1.065],[-1.29,-0.57],[-1.56,0]],"o":[[1.275,-0.57],[0.93,-1.065],[0.51,-1.485],[0,-1.83],[-0.51,-1.5],[-0.93,-1.065],[-1.275,-0.57],[-1.56,0],[-1.29,0.57],[-0.915,1.065],[-0.51,1.5],[0,1.86],[0.51,1.485],[0.915,1.065],[1.29,0.57],[1.56,0]],"v":[[-112.652,-4.515],[-109.345,-6.968],[-107.185,-10.793],[-106.42,-15.81],[-107.185,-20.805],[-109.345,-24.653],[-112.652,-27.105],[-116.905,-27.96],[-121.18,-27.105],[-124.487,-24.653],[-126.625,-20.805],[-127.39,-15.81],[-126.625,-10.793],[-124.487,-6.968],[-121.18,-4.515],[-116.905,-3.66]],"c":true},"ix":2},"nm":"o","mn":"ADBE Vector Shape - Group","hd":false},{"ind":1,"ty":"sh","ix":2,"ks":{"a":0,"k":{"i":[[1.23,1.2],[0,2.46],[0,0],[-1.23,1.2],[-1.95,0],[-1.23,-1.2],[0,-2.46],[0,0],[1.23,-1.2],[1.95,0]],"o":[[-1.23,-1.2],[0,0],[0,-2.46],[1.23,-1.2],[1.95,0],[1.23,1.2],[0,0],[0,2.46],[-1.23,1.2],[-1.95,0]],"v":[[-121.675,-8.655],[-123.52,-14.145],[-123.52,-17.475],[-121.675,-22.965],[-116.905,-24.765],[-112.135,-22.965],[-110.29,-17.475],[-110.29,-14.145],[-112.135,-8.655],[-116.905,-6.855]],"c":true},"ix":2},"nm":"o","mn":"ADBE Vector Shape - Group","hd":false},{"ty":"fl","c":{"a":0,"k":[0.152941176471,0.152941176471,0.152941176471,1],"ix":4},"o":{"a":0,"k":100,"ix":5},"r":1,"bm":0,"nm":"Fill 1","mn":"ADBE Vector Graphic - Fill","hd":false},{"ty":"tr","p":{"a":0,"k":[0,0],"ix":2},"a":{"a":0,"k":[0,0],"ix":1},"s":{"a":0,"k":[100,100],"ix":3},"r":{"a":0,"k":0,"ix":6},"o":{"a":0,"k":100,"ix":7},"sk":{"a":0,"k":0,"ix":4},"sa":{"a":0,"k":0,"ix":5},"nm":"Transform"}],"nm":"o","np":5,"cix":2,"bm":0,"ix":4,"mn":"ADBE Vector Group","hd":false},{"ty":"gr","it":[{"ind":0,"ty":"sh","ix":1,"ks":{"a":0,"k":{"i":[[0,0],[0,0],[0,0],[0,0],[0,0],[0.315,-0.556],[0.525,-0.361],[0.675,-0.18],[0.72,0],[0,4.179],[0,0],[0,0],[0,0],[-1.41,-1.545],[-2.4,0],[-0.72,0.238],[-0.51,0.401],[-0.345,0.52],[-0.24,0.535],[0,0]],"o":[[0,0],[0,0],[0,0],[0,0],[0,0.782],[-0.315,0.556],[-0.525,0.361],[-0.675,0.181],[-3.54,0],[0,0],[0,0],[0,0],[0,2.82],[1.41,1.545],[0.96,0],[0.72,-0.238],[0.51,-0.401],[0.345,-0.52],[0,0],[0,0]],"v":[[-81.04,-4.2],[-77.44,-4.2],[-77.44,-27.42],[-81.04,-27.42],[-81.04,-11.32],[-81.512,-9.313],[-82.772,-7.938],[-84.572,-7.126],[-86.665,-6.855],[-91.975,-13.124],[-91.975,-27.42],[-95.575,-27.42],[-95.575,-12.525],[-93.46,-5.978],[-87.745,-3.66],[-85.225,-4.017],[-83.38,-4.975],[-82.097,-6.356],[-81.22,-7.938],[-81.04,-7.938]],"c":true},"ix":2},"nm":"u","mn":"ADBE Vector Shape - Group","hd":false},{"ty":"fl","c":{"a":0,"k":[0.152941176471,0.152941176471,0.152941176471,1],"ix":4},"o":{"a":0,"k":100,"ix":5},"r":1,"bm":0,"nm":"Fill 1","mn":"ADBE Vector Graphic - Fill","hd":false},{"ty":"tr","p":{"a":0,"k":[0,0],"ix":2},"a":{"a":0,"k":[0,0],"ix":1},"s":{"a":0,"k":[100,100],"ix":3},"r":{"a":0,"k":0,"ix":6},"o":{"a":0,"k":100,"ix":7},"sk":{"a":0,"k":0,"ix":4},"sa":{"a":0,"k":0,"ix":5},"nm":"Transform"}],"nm":"u","np":3,"cix":2,"bm":0,"ix":5,"mn":"ADBE Vector Group","hd":false},{"ty":"gr","it":[{"ind":0,"ty":"sh","ix":1,"ks":{"a":0,"k":{"i":[[0,0],[0,0],[-1.095,0.735],[-1.95,0],[0,0],[0,0],[0,0],[1.08,-0.87],[0.42,-1.11],[0,0],[0,0],[0,0],[0,0]],"o":[[0,0],[0,-1.11],[1.095,-0.735],[0,0],[0,0],[0,0],[-1.89,0],[-1.08,0.87],[0,0],[0,0],[0,0],[0,0],[0,0]],"v":[[-61.06,-4.2],[-61.06,-19.95],[-59.417,-22.718],[-54.85,-23.82],[-52.735,-23.82],[-52.735,-27.42],[-54.13,-27.42],[-58.585,-26.115],[-60.835,-23.145],[-61.06,-23.145],[-61.06,-27.42],[-64.66,-27.42],[-64.66,-4.2]],"c":true},"ix":2},"nm":"r","mn":"ADBE Vector Shape - Group","hd":false},{"ty":"fl","c":{"a":0,"k":[0.152941176471,0.152941176471,0.152941176471,1],"ix":4},"o":{"a":0,"k":100,"ix":5},"r":1,"bm":0,"nm":"Fill 1","mn":"ADBE Vector Graphic - Fill","hd":false},{"ty":"tr","p":{"a":0,"k":[0,0],"ix":2},"a":{"a":0,"k":[0,0],"ix":1},"s":{"a":0,"k":[100,100],"ix":3},"r":{"a":0,"k":0,"ix":6},"o":{"a":0,"k":100,"ix":7},"sk":{"a":0,"k":0,"ix":4},"sa":{"a":0,"k":0,"ix":5},"nm":"Transform"}],"nm":"r","np":3,"cix":2,"bm":0,"ix":6,"mn":"ADBE Vector Group","hd":false},{"ty":"gr","it":[{"ind":0,"ty":"sh","ix":1,"ks":{"a":0,"k":{"i":[[-1.86,1.26],[-0.99,2.22],[0,0],[1.35,-1.035],[2.01,0],[1.5,1.837],[0,3.251],[0,0],[-0.39,1.309],[-0.735,0.949],[-1.065,0.512],[-1.35,0],[-1.29,-0.975],[-0.63,-1.62],[0,0],[1.785,1.185],[2.64,0],[2.22,-2.835],[0,-5.28],[-2.22,-2.715],[-3.99,0]],"o":[[1.86,-1.26],[0,0],[-0.63,1.71],[-1.35,1.035],[-2.73,0],[-1.5,-1.837],[0,0],[0,-1.626],[0.39,-1.309],[0.735,-0.948],[1.065,-0.512],[1.95,0],[1.29,0.975],[0,0],[-0.99,-2.19],[-1.785,-1.185],[-3.99,0],[-2.22,2.835],[0,5.28],[2.22,2.715],[2.64,0]],"v":[[-9.085,-5.55],[-4.81,-10.77],[-7.825,-12.66],[-10.795,-8.543],[-15.835,-6.99],[-22.18,-9.745],[-24.43,-17.376],[-24.43,-22.073],[-23.845,-26.475],[-22.157,-29.862],[-19.457,-32.053],[-15.835,-32.82],[-10.975,-31.358],[-8.095,-27.465],[-5.035,-29.31],[-9.197,-34.373],[-15.835,-36.15],[-25.15,-31.898],[-28.48,-19.725],[-25.15,-7.733],[-15.835,-3.66]],"c":true},"ix":2},"nm":"C","mn":"ADBE Vector Shape - Group","hd":false},{"ty":"fl","c":{"a":0,"k":[0.152941176471,0.152941176471,0.152941176471,1],"ix":4},"o":{"a":0,"k":100,"ix":5},"r":1,"bm":0,"nm":"Fill 1","mn":"ADBE Vector Graphic - Fill","hd":false},{"ty":"tr","p":{"a":0,"k":[0,0],"ix":2},"a":{"a":0,"k":[0,0],"ix":1},"s":{"a":0,"k":[100,100],"ix":3},"r":{"a":0,"k":0,"ix":6},"o":{"a":0,"k":100,"ix":7},"sk":{"a":0,"k":0,"ix":4},"sa":{"a":0,"k":0,"ix":5},"nm":"Transform"}],"nm":"C","np":3,"cix":2,"bm":0,"ix":7,"mn":"ADBE Vector Group","hd":false},{"ty":"gr","it":[{"ind":0,"ty":"sh","ix":1,"ks":{"a":0,"k":{"i":[[-1.275,0.57],[-0.93,1.065],[-0.51,1.485],[0,1.86],[0.51,1.5],[0.93,1.065],[1.275,0.57],[1.56,0],[1.29,-0.57],[0.915,-1.065],[0.51,-1.5],[0,-1.83],[-0.51,-1.485],[-0.915,-1.065],[-1.29,-0.57],[-1.56,0]],"o":[[1.275,-0.57],[0.93,-1.065],[0.51,-1.485],[0,-1.83],[-0.51,-1.5],[-0.93,-1.065],[-1.275,-0.57],[-1.56,0],[-1.29,0.57],[-0.915,1.065],[-0.51,1.5],[0,1.86],[0.51,1.485],[0.915,1.065],[1.29,0.57],[1.56,0]],"v":[[18.838,-4.515],[22.145,-6.968],[24.305,-10.793],[25.07,-15.81],[24.305,-20.805],[22.145,-24.653],[18.838,-27.105],[14.585,-27.96],[10.31,-27.105],[7.003,-24.653],[4.865,-20.805],[4.1,-15.81],[4.865,-10.793],[7.003,-6.968],[10.31,-4.515],[14.585,-3.66]],"c":true},"ix":2},"nm":"o","mn":"ADBE Vector Shape - Group","hd":false},{"ind":1,"ty":"sh","ix":2,"ks":{"a":0,"k":{"i":[[1.23,1.2],[0,2.46],[0,0],[-1.23,1.2],[-1.95,0],[-1.23,-1.2],[0,-2.46],[0,0],[1.23,-1.2],[1.95,0]],"o":[[-1.23,-1.2],[0,0],[0,-2.46],[1.23,-1.2],[1.95,0],[1.23,1.2],[0,0],[0,2.46],[-1.23,1.2],[-1.95,0]],"v":[[9.815,-8.655],[7.97,-14.145],[7.97,-17.475],[9.815,-22.965],[14.585,-24.765],[19.355,-22.965],[21.2,-17.475],[21.2,-14.145],[19.355,-8.655],[14.585,-6.855]],"c":true},"ix":2},"nm":"o","mn":"ADBE Vector Shape - Group","hd":false},{"ty":"fl","c":{"a":0,"k":[0.152941176471,0.152941176471,0.152941176471,1],"ix":4},"o":{"a":0,"k":100,"ix":5},"r":1,"bm":0,"nm":"Fill 1","mn":"ADBE Vector Graphic - Fill","hd":false},{"ty":"tr","p":{"a":0,"k":[0,0],"ix":2},"a":{"a":0,"k":[0,0],"ix":1},"s":{"a":0,"k":[100,100],"ix":3},"r":{"a":0,"k":0,"ix":6},"o":{"a":0,"k":100,"ix":7},"sk":{"a":0,"k":0,"ix":4},"sa":{"a":0,"k":0,"ix":5},"nm":"Transform"}],"nm":"o","np":5,"cix":2,"bm":0,"ix":8,"mn":"ADBE Vector Group","hd":false},{"ty":"gr","it":[{"ind":0,"ty":"sh","ix":1,"ks":{"a":0,"k":{"i":[[0,0],[0,0],[-0.315,0.556],[-0.54,0.361],[-0.675,0.181],[-0.72,0],[0,-4.179],[0,0],[0,0],[0,0],[1.395,1.545],[2.4,0],[1.035,-0.772],[0.57,-1.306],[0,0],[0,0],[0,0],[0,0]],"o":[[0,0],[0,-0.752],[0.315,-0.556],[0.54,-0.361],[0.675,-0.18],[3.51,0],[0,0],[0,0],[0,0],[0,-2.82],[-1.395,-1.545],[-1.74,0],[-1.035,0.772],[0,0],[0,0],[0,0],[0,0],[0,0]],"v":[[39.74,-4.2],[39.74,-20.346],[40.213,-22.307],[41.495,-23.683],[43.318,-24.495],[45.41,-24.765],[50.675,-18.496],[50.675,-4.2],[54.275,-4.2],[54.275,-19.095],[52.183,-25.643],[46.49,-27.96],[42.328,-26.802],[39.92,-23.683],[39.74,-23.683],[39.74,-27.42],[36.14,-27.42],[36.14,-4.2]],"c":true},"ix":2},"nm":"n","mn":"ADBE Vector Shape - Group","hd":false},{"ty":"fl","c":{"a":0,"k":[0.152941176471,0.152941176471,0.152941176471,1],"ix":4},"o":{"a":0,"k":100,"ix":5},"r":1,"bm":0,"nm":"Fill 1","mn":"ADBE Vector Graphic - Fill","hd":false},{"ty":"tr","p":{"a":0,"k":[0,0],"ix":2},"a":{"a":0,"k":[0,0],"ix":1},"s":{"a":0,"k":[100,100],"ix":3},"r":{"a":0,"k":0,"ix":6},"o":{"a":0,"k":100,"ix":7},"sk":{"a":0,"k":0,"ix":4},"sa":{"a":0,"k":0,"ix":5},"nm":"Transform"}],"nm":"n","np":3,"cix":2,"bm":0,"ix":9,"mn":"ADBE Vector Group","hd":false},{"ty":"gr","it":[{"ind":0,"ty":"sh","ix":1,"ks":{"a":0,"k":{"i":[[0,0],[0,0],[0,0],[0,0],[0,0],[0,0],[1.155,0.698],[1.62,0],[1.17,-0.57],[0.825,-1.05],[0.435,-1.5],[0,-1.86],[-0.435,-1.5],[-0.825,-1.05],[-1.17,-0.57],[-1.44,0],[-1.41,2.852],[0,0]],"o":[[0,0],[0,0],[0,0],[0,0],[0,0],[-0.6,-1.455],[-1.155,-0.698],[-1.44,0],[-1.17,0.57],[-0.825,1.05],[-0.435,1.5],[0,1.86],[0.435,1.5],[0.825,1.05],[1.17,0.57],[3.12,0],[0,0],[0,0]],"v":[[81.68,-4.2],[85.28,-4.2],[85.28,-37.5],[81.68,-37.5],[81.68,-23.683],[81.5,-23.683],[78.868,-26.913],[74.705,-27.96],[70.79,-27.105],[67.798,-24.675],[65.908,-20.85],[65.255,-15.81],[65.908,-10.77],[67.798,-6.945],[70.79,-4.515],[74.705,-3.66],[81.5,-7.938],[81.68,-7.938]],"c":true},"ix":2},"nm":"d","mn":"ADBE Vector Shape - Group","hd":false},{"ind":1,"ty":"sh","ix":2,"ks":{"a":0,"k":{"i":[[1.17,1.281],[0,2.081],[0,0],[-1.17,1.281],[-2.04,0],[-0.735,-0.226],[-0.54,-0.392],[-0.315,-0.558],[0,-0.633],[0,0],[0.315,-0.588],[0.54,-0.406],[0.735,-0.211],[0.81,0]],"o":[[-1.17,-1.281],[0,0],[0,-2.081],[1.17,-1.281],[0.81,0],[0.735,0.226],[0.54,0.392],[0.315,0.558],[0,0],[0,0.754],[-0.315,0.588],[-0.54,0.407],[-0.735,0.211],[-2.04,0]],"v":[[70.88,-8.777],[69.125,-13.821],[69.125,-17.8],[70.88,-22.843],[75.695,-24.765],[78.013,-24.426],[79.925,-23.499],[81.208,-22.075],[81.68,-20.288],[81.68,-11.604],[81.208,-9.591],[79.925,-8.099],[78.013,-7.172],[75.695,-6.855]],"c":true},"ix":2},"nm":"d","mn":"ADBE Vector Shape - Group","hd":false},{"ty":"fl","c":{"a":0,"k":[0.152941176471,0.152941176471,0.152941176471,1],"ix":4},"o":{"a":0,"k":100,"ix":5},"r":1,"bm":0,"nm":"Fill 1","mn":"ADBE Vector Graphic - Fill","hd":false},{"ty":"tr","p":{"a":0,"k":[0,0],"ix":2},"a":{"a":0,"k":[0,0],"ix":1},"s":{"a":0,"k":[100,100],"ix":3},"r":{"a":0,"k":0,"ix":6},"o":{"a":0,"k":100,"ix":7},"sk":{"a":0,"k":0,"ix":4},"sa":{"a":0,"k":0,"ix":5},"nm":"Transform"}],"nm":"d","np":5,"cix":2,"bm":0,"ix":10,"mn":"ADBE Vector Group","hd":false},{"ty":"gr","it":[{"ind":0,"ty":"sh","ix":1,"ks":{"a":0,"k":{"i":[[-0.345,0.375],[0,0.6],[0,0],[0.345,0.375],[0.78,0],[0.345,-0.375],[0,-0.6],[0,0],[-0.345,-0.375],[-0.78,0]],"o":[[0.345,-0.375],[0,0],[0,-0.6],[-0.345,-0.375],[-0.78,0],[-0.345,0.375],[0,0],[0,0.6],[0.345,0.375],[0.78,0]],"v":[[101.548,-33.428],[102.065,-34.89],[102.065,-35.475],[101.548,-36.938],[99.86,-37.5],[98.173,-36.938],[97.655,-35.475],[97.655,-34.89],[98.173,-33.428],[99.86,-32.865]],"c":true},"ix":2},"nm":"i","mn":"ADBE Vector Shape - Group","hd":false},{"ind":1,"ty":"sh","ix":2,"ks":{"a":0,"k":{"i":[[0,0],[0,0],[0,0],[0,0]],"o":[[0,0],[0,0],[0,0],[0,0]],"v":[[98.06,-4.2],[101.66,-4.2],[101.66,-27.42],[98.06,-27.42]],"c":true},"ix":2},"nm":"i","mn":"ADBE Vector Shape - Group","hd":false},{"ty":"fl","c":{"a":0,"k":[0.152941176471,0.152941176471,0.152941176471,1],"ix":4},"o":{"a":0,"k":100,"ix":5},"r":1,"bm":0,"nm":"Fill 1","mn":"ADBE Vector Graphic - Fill","hd":false},{"ty":"tr","p":{"a":0,"k":[0,0],"ix":2},"a":{"a":0,"k":[0,0],"ix":1},"s":{"a":0,"k":[100,100],"ix":3},"r":{"a":0,"k":0,"ix":6},"o":{"a":0,"k":100,"ix":7},"sk":{"a":0,"k":0,"ix":4},"sa":{"a":0,"k":0,"ix":5},"nm":"Transform"}],"nm":"i","np":5,"cix":2,"bm":0,"ix":11,"mn":"ADBE Vector Group","hd":false},{"ty":"gr","it":[{"ind":0,"ty":"sh","ix":1,"ks":{"a":0,"k":{"i":[[0,0],[0,0],[0,0],[0,0],[0,0],[0,0],[0,0],[0,0],[0,0],[0,0],[0.285,-0.315],[0.78,0],[0,0],[0,0],[0,0],[0,0],[-0.645,-0.703],[-1.26,0]],"o":[[0,0],[0,0],[0,0],[0,0],[0,0],[0,0],[0,0],[0,0],[0,0],[0,0.78],[-0.285,0.315],[0,0],[0,0],[0,0],[0,0],[0,1.138],[0.645,0.703],[0,0]],"v":[[124.07,-4.2],[124.07,-7.395],[119.345,-7.395],[119.345,-24.225],[124.43,-24.225],[124.43,-27.42],[119.345,-27.42],[119.345,-33.855],[116.105,-33.855],[116.105,-29.535],[115.678,-27.893],[114.08,-27.42],[111.92,-27.42],[111.92,-24.225],[115.745,-24.225],[115.745,-8.017],[116.713,-5.255],[119.57,-4.2]],"c":true},"ix":2},"nm":"t","mn":"ADBE Vector Shape - Group","hd":false},{"ty":"fl","c":{"a":0,"k":[0.152941176471,0.152941176471,0.152941176471,1],"ix":4},"o":{"a":0,"k":100,"ix":5},"r":1,"bm":0,"nm":"Fill 1","mn":"ADBE Vector Graphic - Fill","hd":false},{"ty":"tr","p":{"a":0,"k":[0,0],"ix":2},"a":{"a":0,"k":[0,0],"ix":1},"s":{"a":0,"k":[100,100],"ix":3},"r":{"a":0,"k":0,"ix":6},"o":{"a":0,"k":100,"ix":7},"sk":{"a":0,"k":0,"ix":4},"sa":{"a":0,"k":0,"ix":5},"nm":"Transform"}],"nm":"t","np":3,"cix":2,"bm":0,"ix":12,"mn":"ADBE Vector Group","hd":false},{"ty":"gr","it":[{"ind":0,"ty":"sh","ix":1,"ks":{"a":0,"k":{"i":[[-0.345,0.375],[0,0.6],[0,0],[0.345,0.375],[0.78,0],[0.345,-0.375],[0,-0.6],[0,0],[-0.345,-0.375],[-0.78,0]],"o":[[0.345,-0.375],[0,0],[0,-0.6],[-0.345,-0.375],[-0.78,0],[-0.345,0.375],[0,0],[0,0.6],[0.345,0.375],[0.78,0]],"v":[[138.853,-33.428],[139.37,-34.89],[139.37,-35.475],[138.853,-36.938],[137.165,-37.5],[135.478,-36.938],[134.96,-35.475],[134.96,-34.89],[135.478,-33.428],[137.165,-32.865]],"c":true},"ix":2},"nm":"i","mn":"ADBE Vector Shape - Group","hd":false},{"ind":1,"ty":"sh","ix":2,"ks":{"a":0,"k":{"i":[[0,0],[0,0],[0,0],[0,0]],"o":[[0,0],[0,0],[0,0],[0,0]],"v":[[135.365,-4.2],[138.965,-4.2],[138.965,-27.42],[135.365,-27.42]],"c":true},"ix":2},"nm":"i","mn":"ADBE Vector Shape - Group","hd":false},{"ty":"fl","c":{"a":0,"k":[0.152941176471,0.152941176471,0.152941176471,1],"ix":4},"o":{"a":0,"k":100,"ix":5},"r":1,"bm":0,"nm":"Fill 1","mn":"ADBE Vector Graphic - Fill","hd":false},{"ty":"tr","p":{"a":0,"k":[0,0],"ix":2},"a":{"a":0,"k":[0,0],"ix":1},"s":{"a":0,"k":[100,100],"ix":3},"r":{"a":0,"k":0,"ix":6},"o":{"a":0,"k":100,"ix":7},"sk":{"a":0,"k":0,"ix":4},"sa":{"a":0,"k":0,"ix":5},"nm":"Transform"}],"nm":"i","np":5,"cix":2,"bm":0,"ix":13,"mn":"ADBE Vector Group","hd":false},{"ty":"gr","it":[{"ind":0,"ty":"sh","ix":1,"ks":{"a":0,"k":{"i":[[-1.275,0.57],[-0.93,1.065],[-0.51,1.485],[0,1.86],[0.51,1.5],[0.93,1.065],[1.275,0.57],[1.56,0],[1.29,-0.57],[0.915,-1.065],[0.51,-1.5],[0,-1.83],[-0.51,-1.485],[-0.915,-1.065],[-1.29,-0.57],[-1.56,0]],"o":[[1.275,-0.57],[0.93,-1.065],[0.51,-1.485],[0,-1.83],[-0.51,-1.5],[-0.93,-1.065],[-1.275,-0.57],[-1.56,0],[-1.29,0.57],[-0.915,1.065],[-0.51,1.5],[0,1.86],[0.51,1.485],[0.915,1.065],[1.29,0.57],[1.56,0]],"v":[[164.773,-4.515],[168.08,-6.968],[170.24,-10.793],[171.005,-15.81],[170.24,-20.805],[168.08,-24.653],[164.773,-27.105],[160.52,-27.96],[156.245,-27.105],[152.938,-24.653],[150.8,-20.805],[150.035,-15.81],[150.8,-10.793],[152.938,-6.968],[156.245,-4.515],[160.52,-3.66]],"c":true},"ix":2},"nm":"o","mn":"ADBE Vector Shape - Group","hd":false},{"ind":1,"ty":"sh","ix":2,"ks":{"a":0,"k":{"i":[[1.23,1.2],[0,2.46],[0,0],[-1.23,1.2],[-1.95,0],[-1.23,-1.2],[0,-2.46],[0,0],[1.23,-1.2],[1.95,0]],"o":[[-1.23,-1.2],[0,0],[0,-2.46],[1.23,-1.2],[1.95,0],[1.23,1.2],[0,0],[0,2.46],[-1.23,1.2],[-1.95,0]],"v":[[155.75,-8.655],[153.905,-14.145],[153.905,-17.475],[155.75,-22.965],[160.52,-24.765],[165.29,-22.965],[167.135,-17.475],[167.135,-14.145],[165.29,-8.655],[160.52,-6.855]],"c":true},"ix":2},"nm":"o","mn":"ADBE Vector Shape - Group","hd":false},{"ty":"fl","c":{"a":0,"k":[0.152941176471,0.152941176471,0.152941176471,1],"ix":4},"o":{"a":0,"k":100,"ix":5},"r":1,"bm":0,"nm":"Fill 1","mn":"ADBE Vector Graphic - Fill","hd":false},{"ty":"tr","p":{"a":0,"k":[0,0],"ix":2},"a":{"a":0,"k":[0,0],"ix":1},"s":{"a":0,"k":[100,100],"ix":3},"r":{"a":0,"k":0,"ix":6},"o":{"a":0,"k":100,"ix":7},"sk":{"a":0,"k":0,"ix":4},"sa":{"a":0,"k":0,"ix":5},"nm":"Transform"}],"nm":"o","np":5,"cix":2,"bm":0,"ix":14,"mn":"ADBE Vector Group","hd":false},{"ty":"gr","it":[{"ind":0,"ty":"sh","ix":1,"ks":{"a":0,"k":{"i":[[0,0],[0,0],[-0.315,0.556],[-0.54,0.361],[-0.675,0.181],[-0.72,0],[0,-4.179],[0,0],[0,0],[0,0],[1.395,1.545],[2.4,0],[1.035,-0.772],[0.57,-1.306],[0,0],[0,0],[0,0],[0,0]],"o":[[0,0],[0,-0.752],[0.315,-0.556],[0.54,-0.361],[0.675,-0.18],[3.51,0],[0,0],[0,0],[0,0],[0,-2.82],[-1.395,-1.545],[-1.74,0],[-1.035,0.772],[0,0],[0,0],[0,0],[0,0],[0,0]],"v":[[185.675,-4.2],[185.675,-20.346],[186.148,-22.307],[187.43,-23.683],[189.253,-24.495],[191.345,-24.765],[196.61,-18.496],[196.61,-4.2],[200.21,-4.2],[200.21,-19.095],[198.118,-25.643],[192.425,-27.96],[188.263,-26.802],[185.855,-23.683],[185.675,-23.683],[185.675,-27.42],[182.075,-27.42],[182.075,-4.2]],"c":true},"ix":2},"nm":"n","mn":"ADBE Vector Shape - Group","hd":false},{"ty":"fl","c":{"a":0,"k":[0.152941176471,0.152941176471,0.152941176471,1],"ix":4},"o":{"a":0,"k":100,"ix":5},"r":1,"bm":0,"nm":"Fill 1","mn":"ADBE Vector Graphic - Fill","hd":false},{"ty":"tr","p":{"a":0,"k":[0,0],"ix":2},"a":{"a":0,"k":[0,0],"ix":1},"s":{"a":0,"k":[100,100],"ix":3},"r":{"a":0,"k":0,"ix":6},"o":{"a":0,"k":100,"ix":7},"sk":{"a":0,"k":0,"ix":4},"sa":{"a":0,"k":0,"ix":5},"nm":"Transform"}],"nm":"n","np":3,"cix":2,"bm":0,"ix":15,"mn":"ADBE Vector Group","hd":false},{"ty":"gr","it":[{"ind":0,"ty":"sh","ix":1,"ks":{"a":0,"k":{"i":[[-1.53,1.29],[0,2.25],[1.08,1.095],[2.58,0.39],[0,0],[0.765,0.51],[0,1.14],[-0.765,0.645],[-1.5,0],[-0.99,-0.585],[-0.51,-0.72],[0,0],[1.275,0.66],[1.89,0],[1.02,-0.285],[0.735,-0.57],[0.42,-0.855],[0,-1.14],[-0.375,-0.78],[-0.675,-0.525],[-0.9,-0.315],[-1.08,-0.15],[0,0],[-0.585,-0.645],[0,-0.9],[0.855,-0.66],[1.53,0],[1.11,0.615],[0.9,1.14],[0,0],[-1.455,-0.825],[-2.16,0]],"o":[[1.53,-1.29],[0,-1.77],[-1.08,-1.095],[0,0],[-1.44,-0.24],[-0.765,-0.51],[0,-1.11],[0.765,-0.645],[1.5,0],[0.99,0.585],[0,0],[-0.96,-1.17],[-1.275,-0.66],[-1.17,0],[-1.02,0.285],[-0.735,0.57],[-0.42,0.855],[0,1.08],[0.375,0.78],[0.675,0.525],[0.9,0.315],[0,0],[1.53,0.24],[0.585,0.645],[0,1.2],[-0.855,0.66],[-1.47,0],[-1.11,-0.615],[0,0],[1.05,1.38],[1.455,0.825],[2.67,0]],"v":[[226.04,-5.595],[228.335,-10.905],[226.715,-15.203],[221.225,-17.43],[219.425,-17.7],[216.118,-18.825],[214.97,-21.3],[216.118,-23.933],[219.515,-24.9],[223.25,-24.023],[225.5,-22.065],[227.885,-24.225],[224.533,-26.97],[219.785,-27.96],[216.5,-27.533],[213.868,-26.25],[212.135,-24.113],[211.505,-21.12],[212.068,-18.33],[213.643,-16.373],[216.005,-15.113],[218.975,-14.415],[220.82,-14.145],[223.993,-12.818],[224.87,-10.5],[223.588,-7.71],[220.01,-6.72],[216.14,-7.643],[213.125,-10.275],[210.56,-8.205],[214.318,-4.898],[219.74,-3.66]],"c":true},"ix":2},"nm":"s","mn":"ADBE Vector Shape - Group","hd":false},{"ty":"fl","c":{"a":0,"k":[0.152941176471,0.152941176471,0.152941176471,1],"ix":4},"o":{"a":0,"k":100,"ix":5},"r":1,"bm":0,"nm":"Fill 1","mn":"ADBE Vector Graphic - Fill","hd":false},{"ty":"tr","p":{"a":0,"k":[0,0],"ix":2},"a":{"a":0,"k":[0,0],"ix":1},"s":{"a":0,"k":[100,100],"ix":3},"r":{"a":0,"k":0,"ix":6},"o":{"a":0,"k":100,"ix":7},"sk":{"a":0,"k":0,"ix":4},"sa":{"a":0,"k":0,"ix":5},"nm":"Transform"}],"nm":"s","np":3,"cix":2,"bm":0,"ix":16,"mn":"ADBE Vector Group","hd":false}],"ip":0,"op":1800,"st":0,"bm":0},{"ddd":0,"ind":5,"ty":4,"nm":"Shape Layer 4","td":1,"sr":1,"ks":{"o":{"a":0,"k":100,"ix":11},"r":{"a":0,"k":0,"ix":10},"p":{"a":0,"k":[300,200,0],"ix":2},"a":{"a":0,"k":[0,0,0],"ix":1},"s":{"a":0,"k":[100,100,100],"ix":6}},"ao":0,"shapes":[{"ty":"gr","it":[{"ind":0,"ty":"sh","ix":1,"ks":{"a":0,"k":{"i":[[0,0]],"o":[[0,0]],"v":[[233.5,-37]],"c":false},"ix":2},"nm":"Path 1","mn":"ADBE Vector Shape - Group","hd":false},{"ty":"st","c":{"a":0,"k":[1,0,0,1],"ix":3},"o":{"a":0,"k":100,"ix":4},"w":{"a":0,"k":45,"ix":5},"lc":1,"lj":1,"ml":4,"bm":0,"nm":"Stroke 1","mn":"ADBE Vector Graphic - Stroke","hd":false},{"ty":"tr","p":{"a":0,"k":[0,0],"ix":2},"a":{"a":0,"k":[0,0],"ix":1},"s":{"a":0,"k":[100,100],"ix":3},"r":{"a":0,"k":0,"ix":6},"o":{"a":0,"k":100,"ix":7},"sk":{"a":0,"k":0,"ix":4},"sa":{"a":0,"k":0,"ix":5},"nm":"Transform"}],"nm":"Shape 2","np":3,"cix":2,"bm":0,"ix":1,"mn":"ADBE Vector Group","hd":false},{"ty":"gr","it":[{"ind":0,"ty":"sh","ix":1,"ks":{"a":0,"k":{"i":[[0,0],[0,0],[0,0],[0,0],[0,0],[0,0],[0,0],[0,0],[0,0],[0,0],[0,0],[0,0],[0,0],[0,0],[0,0],[0,0],[0,0],[0,0],[0,0],[0,0],[0,0],[0,0],[0,0],[0,0],[0,0],[0,0],[0,0],[0,0],[0,0],[0,0],[0,0],[0,0],[0,0],[0,0],[0,0],[0,0],[0,0],[0,0],[0,0],[0,0],[0,0],[0,0],[0,0],[0,0],[0,0],[0,0],[0,0],[0,0],[0,0],[0,0],[0,0],[0,0]],"o":[[0,0],[0,0],[0,0],[0,0],[0,0],[0,0],[0,0],[0,0],[0,0],[0,0],[0,0],[0,0],[0,0],[0,0],[0,0],[0,0],[0,0],[0,0],[0,0],[0,0],[0,0],[0,0],[0,0],[0,0],[0,0],[0,0],[0,0],[0,0],[0,0],[0,0],[0,0],[0,0],[0,0],[0,0],[0,0],[0,0],[0,0],[0,0],[0,0],[0,0],[0,0],[0,0],[0,0],[0,0],[0,0],[0,0],[0,0],[0,0],[0,0],[0,0],[0,0],[0,0]],"v":[[238.777,-33.432],[253.503,2.866],[330.291,-27.701],[179.872,-22.447],[180.924,-32.955],[231.983,-78.9],[270.859,121.789],[279.014,-23.907],[263.12,-111.394],[328.713,-68.297],[277.697,-84.536],[225.629,-71.163],[196.176,-66.865],[173.56,-61.133],[176.716,-49.671],[198.806,-53.969],[198.806,-33.91],[196.702,-9.074],[200.909,16.716],[203.539,59.223],[204.065,101.252],[289.793,31.044],[284.534,56.357],[268.756,67.82],[232.992,64.476],[216.162,67.82],[183.553,65.431],[157.782,48.238],[147.263,37.731],[139.374,22.925],[130.959,5.254],[123.596,-17.671],[90.462,-4.298],[48.387,8.119],[31.031,27.223],[136.278,68.112],[74.163,70.022],[113.123,62.342],[104.708,40.422],[101.552,17.366],[104.311,-5.478],[104.978,-102.035],[47.01,-97.186],[141.335,-95.909],[140.882,-17.216],[156.156,-19.186],[160.526,-29.045],[157.974,-50.403],[153.571,-67.91],[144.193,-75.03],[121.96,-79.962],[60.118,-83.873]],"c":false},"ix":2},"nm":"Path 1","mn":"ADBE Vector Shape - Group","hd":false},{"ty":"tm","s":{"a":1,"k":[{"i":{"x":[0.833],"y":[0.833]},"o":{"x":[0.167],"y":[0.167]},"t":92.092,"s":[100]},{"t":108.107421875,"s":[0]}],"ix":1},"e":{"a":0,"k":100,"ix":2},"o":{"a":0,"k":0,"ix":3},"m":2,"ix":2,"nm":"Trim Paths 1","mn":"ADBE Vector Filter - Trim","hd":false},{"ty":"st","c":{"a":0,"k":[1,0,0,1],"ix":3},"o":{"a":0,"k":100,"ix":4},"w":{"a":0,"k":45,"ix":5},"lc":1,"lj":1,"ml":4,"bm":0,"nm":"Stroke 1","mn":"ADBE Vector Graphic - Stroke","hd":false},{"ty":"tr","p":{"a":0,"k":[0,0],"ix":2},"a":{"a":0,"k":[0,0],"ix":1},"s":{"a":0,"k":[95.068,104.689],"ix":3},"r":{"a":0,"k":0,"ix":6},"o":{"a":0,"k":100,"ix":7},"sk":{"a":0,"k":0,"ix":4},"sa":{"a":0,"k":0,"ix":5},"nm":"Transform"}],"nm":"Shape 1","np":4,"cix":2,"bm":0,"ix":2,"mn":"ADBE Vector Group","hd":false}],"ip":0,"op":1801.8018018018,"st":0,"bm":0},{"ddd":0,"ind":6,"ty":4,"nm":"RE","tt":1,"sr":1,"ks":{"o":{"a":0,"k":100,"ix":11},"r":{"a":0,"k":0,"ix":10},"p":{"a":0,"k":[300,200,0],"ix":2},"a":{"a":0,"k":[960,540,0],"ix":1},"s":{"a":0,"k":[100,100,100],"ix":6}},"ao":0,"shapes":[{"ty":"gr","it":[{"ind":0,"ty":"sh","ix":1,"ks":{"a":0,"k":{"i":[[9.832,0],[2.662,0.385],[0,0],[-0.482,0.181],[-4.071,0],[-4.694,-4.538],[0,-8.976],[5.323,-4.555]],"o":[[-3.244,0],[0,0],[0,-0.895],[3.52,-1.051],[9.022,0],[4.722,4.57],[0,9.603],[-5.431,4.648]],"v":[[-55.007,-6.524],[-63.886,-7.104],[-63.886,-58.75],[-63.221,-59.956],[-51.783,-61.542],[-31.112,-54.701],[-24.095,-34.57],[-32.005,-13.529]],"c":true},"ix":2},"nm":"Path 1","mn":"ADBE Vector Shape - Group","hd":false},{"ind":1,"ty":"sh","ix":2,"ks":{"a":0,"k":{"i":[[0.595,0.16],[0,0],[0.176,-0.567],[1.634,-3.463],[1.823,-0.996],[4.073,0],[0,0],[0.543,0.157],[0.103,0.348],[0,2.916],[0,0],[-0.61,0],[0,0],[-2.799,-4.511],[-2.478,-3.915],[-0.491,0.244],[0,0],[0.324,0.552],[0,0],[0.526,-0.302],[0,0],[-0.316,-0.531],[0,0],[13.172,0],[0,0],[0,0.61],[0,0],[-0.195,0.195],[-0.957,0],[0,0],[-1.151,-0.605],[-0.847,-2.712],[-0.481,-3.493],[-0.584,0.047],[0,0],[0.065,0.618],[0,0],[0,0],[0.568,0],[0,0],[0,-0.611],[0,0],[-0.588,-0.029],[-1.225,-0.342],[-0.333,-0.768],[0,-4.417],[0,0],[0.311,-0.716],[0.915,-0.256],[1.892,-0.184],[1.534,0.622],[1.058,1.398],[2.277,4.096],[0,0],[1.541,2.214],[-5.384,5.434],[0,12.033],[7.906,7.035],[14.681,0],[0,0],[0,-0.61],[0,0],[-0.588,-0.03],[-1.226,-0.341],[-0.333,-0.766],[0,-4.417],[0,0],[0.308,-0.713],[0.915,-0.256],[2.745,-0.139],[0,-0.588],[0,0],[-0.61,0],[0,0],[0,0.61],[0,0],[0.588,0.03],[1.225,0.341],[0.335,0.773],[0,4.423],[0,0],[-2.666,0],[0,0],[0,0],[-2.134,-2.53],[-3.939,-1.114],[-4.614,-0.182],[-0.154,0],[0,0],[-0.019,0],[0,0],[0,0],[0,0],[-0.128,0.486],[0,0],[0,0]],"o":[[0,0],[-0.574,-0.155],[-1.135,3.662],[-1.628,3.443],[-2.02,1.102],[0,0],[-1.659,0],[-0.349,-0.101],[-0.214,-0.722],[0,0],[0,-0.61],[0,0],[7.322,0],[0.791,1.274],[0.293,0.464],[0,0],[0.573,-0.285],[0,0],[-0.307,-0.522],[0,0],[-0.536,0.307],[0,0],[3.309,5.904],[0,0],[-0.61,0],[0,0],[0,-1.919],[0.657,-0.656],[0,0],[4.948,0],[1.267,0.667],[0.936,2.999],[0.08,0.58],[0,0],[0.619,-0.05],[0,0],[0,0],[-0.056,-0.565],[0,0],[-0.611,0],[0,0],[0,0.588],[2.744,0.139],[0.914,0.256],[0.312,0.719],[0,0],[0,4.415],[-0.334,0.77],[-0.837,0.234],[-2.628,-0.149],[-1.84,-0.744],[-1.363,-1.797],[0,0],[-1.967,-4.051],[8.31,-2.383],[7.071,-7.136],[0,-12.486],[-7.771,-6.914],[0,0],[-0.61,0],[0,0],[0,0.589],[2.745,0.139],[0.915,0.256],[0.312,0.72],[0,0],[0,4.414],[-0.335,0.772],[-1.225,0.341],[-0.588,0.03],[0,0],[0,0.61],[0,0],[0.61,0],[0,0],[0,-0.589],[-2.75,-0.139],[-0.915,-0.256],[-0.311,-0.714],[0,0],[2.765,0.26],[0,0],[0,0],[2.916,5.833],[2.426,2.885],[2.686,0.761],[0.133,0.056],[0,0],[0.018,0],[0,0],[0,0],[0,0],[0.502,0],[0,0],[0,0],[0.169,-0.593]],"v":[[97.439,35.351],[87.128,32.575],[85.785,33.315],[79.108,52.915],[73.831,59.702],[64.648,61.361],[34.914,61.361],[31.734,61.029],[31.011,60.316],[30.512,55.168],[30.512,-5.689],[31.617,-6.794],[45.825,-6.794],[60.111,-3.078],[63.456,2.487],[64.886,2.891],[72.972,-1.138],[73.432,-2.686],[55.302,-33.606],[53.799,-34.005],[47.553,-30.427],[47.153,-28.902],[48.424,-26.772],[34.061,-21.908],[31.617,-21.908],[30.512,-23.013],[30.512,-57.855],[31.305,-60.568],[34.198,-61.362],[64.648,-61.362],[73.164,-60.033],[76.396,-54.867],[79.415,-37.023],[80.597,-36.078],[90.898,-36.904],[91.909,-38.122],[88.705,-68.464],[88.085,-74.668],[86.985,-75.663],[-2.873,-75.663],[-3.979,-74.558],[-3.979,-64.921],[-2.932,-63.818],[8.311,-62.943],[10.719,-61.453],[11.553,-54.451],[11.553,54.452],[10.72,61.45],[8.31,62.942],[4.528,63.618],[-1.736,62.461],[-6.042,59.279],[-11.528,50.398],[-30.463,14.134],[-35.678,4.82],[-15.076,-6.935],[-4.42,-35.824],[-16.334,-65.243],[-50.171,-75.663],[-97.278,-75.663],[-98.383,-74.558],[-98.383,-64.921],[-97.336,-63.818],[-86.088,-62.943],[-83.68,-61.454],[-82.846,-54.451],[-82.846,54.453],[-83.677,61.448],[-86.089,62.943],[-97.336,63.818],[-98.383,64.921],[-98.383,74.559],[-97.278,75.664],[-49.428,75.664],[-48.323,74.559],[-48.323,64.922],[-49.37,63.818],[-60.644,62.943],[-63.055,61.448],[-63.886,54.453],[-63.886,7.029],[-55.723,7.42],[-54.958,7.42],[-30.299,55.711],[-22.794,68.142],[-13.202,74.168],[-2.312,75.575],[-1.879,75.663],[2.437,75.663],[2.491,75.664],[8.067,75.664],[8.067,75.663],[86.416,75.663],[87.485,74.839],[88.93,69.341],[98.214,36.721]],"c":true},"ix":2},"nm":"Path 2","mn":"ADBE Vector Shape - Group","hd":false},{"ty":"st","c":{"a":0,"k":[0,0,0,1],"ix":3},"o":{"a":0,"k":100,"ix":4},"w":{"a":0,"k":1,"ix":5},"lc":1,"lj":1,"ml":10,"bm":0,"nm":"Stroke 1","mn":"ADBE Vector Graphic - Stroke","hd":false},{"ty":"fl","c":{"a":0,"k":[0.101960791794,0.101960791794,0.101960791794,1],"ix":4},"o":{"a":0,"k":100,"ix":5},"r":1,"bm":0,"nm":"Fill 1","mn":"ADBE Vector Graphic - Fill","hd":false},{"ty":"tr","p":{"a":0,"k":[1134.866,540.319],"ix":2},"a":{"a":0,"k":[0,0],"ix":1},"s":{"a":0,"k":[100,100],"ix":3},"r":{"a":0,"k":0,"ix":6},"o":{"a":0,"k":100,"ix":7},"sk":{"a":0,"k":0,"ix":4},"sa":{"a":0,"k":0,"ix":5},"nm":"Transform"}],"nm":"Group 1","np":4,"cix":2,"bm":0,"ix":1,"mn":"ADBE Vector Group","hd":false}],"ip":0,"op":1801.8018018018,"st":0,"bm":0},{"ddd":0,"ind":7,"ty":4,"nm":"Shape Layer 3","td":1,"sr":1,"ks":{"o":{"a":0,"k":100,"ix":11},"r":{"a":0,"k":0,"ix":10},"p":{"a":0,"k":[297,210,0],"ix":2},"a":{"a":0,"k":[0,0,0],"ix":1},"s":{"a":0,"k":[100,100,100],"ix":6}},"ao":0,"shapes":[{"ty":"gr","it":[{"ind":0,"ty":"sh","ix":1,"ks":{"a":0,"k":{"i":[[0,0],[0,0],[0,0],[0,0],[0,0],[0,0],[0,0],[0,0],[0,0],[0,0],[0,0],[0,0],[0,0],[0,0],[0,0],[0,0],[0,0],[0,0],[0,0],[0,0],[0,0],[0,0],[0,0],[0,0],[0,0],[0,0],[0,0],[0,0],[0,0],[0,0],[0,0]],"o":[[0,0],[0,0],[0,0],[0,0],[0,0],[0,0],[0,0],[0,0],[0,0],[0,0],[0,0],[0,0],[0,0],[0,0],[0,0],[0,0],[0,0],[0,0],[0,0],[0,0],[0,0],[0,0],[0,0],[0,0],[0,0],[0,0],[0,0],[0,0],[0,0],[0,0],[0,0]],"v":[[-64,71],[-7,72],[11,67],[31,65],[42,71],[99,73],[94,57],[72,40],[31,37],[-4,37],[-39,38],[-55,10],[-22,8],[24,8],[73,6],[81,-12],[68,-26],[26,-25],[-31,-23],[-50,-28],[-74,-45],[-61,-63],[-22,-51],[22,-60],[65,-60],[97,-62],[91,-79],[43,-83],[2,-84],[-32,-84],[-61,-84]],"c":false},"ix":2},"nm":"Path 1","mn":"ADBE Vector Shape - Group","hd":false},{"ty":"st","c":{"a":0,"k":[1,0,0,1],"ix":3},"o":{"a":0,"k":100,"ix":4},"w":{"a":0,"k":35,"ix":5},"lc":1,"lj":1,"ml":4,"bm":0,"nm":"Stroke 1","mn":"ADBE Vector Graphic - Stroke","hd":false},{"ty":"tr","p":{"a":0,"k":[0,0],"ix":2},"a":{"a":0,"k":[0,0],"ix":1},"s":{"a":0,"k":[100,100],"ix":3},"r":{"a":0,"k":0,"ix":6},"o":{"a":0,"k":100,"ix":7},"sk":{"a":0,"k":0,"ix":4},"sa":{"a":0,"k":0,"ix":5},"nm":"Transform"}],"nm":"Shape 1","np":3,"cix":2,"bm":0,"ix":1,"mn":"ADBE Vector Group","hd":false},{"ty":"tm","s":{"a":1,"k":[{"i":{"x":[0.667],"y":[1]},"o":{"x":[0.167],"y":[0.167]},"t":78.078,"s":[0]},{"t":94.09375,"s":[100]}],"ix":1},"e":{"a":0,"k":0,"ix":2},"o":{"a":0,"k":0,"ix":3},"m":1,"ix":2,"nm":"Trim Paths 1","mn":"ADBE Vector Filter - Trim","hd":false}],"ip":0,"op":1801.8018018018,"st":0,"bm":0},{"ddd":0,"ind":8,"ty":4,"nm":"H","tt":1,"sr":1,"ks":{"o":{"a":0,"k":100,"ix":11},"r":{"a":0,"k":0,"ix":10},"p":{"a":0,"k":[300,200,0],"ix":2},"a":{"a":0,"k":[960,540,0],"ix":1},"s":{"a":0,"k":[100,100,100],"ix":6}},"ao":0,"shapes":[{"ty":"gr","it":[{"ind":0,"ty":"sh","ix":1,"ks":{"a":0,"k":{"i":[[0,-4.424],[0,0],[-0.31,-0.714],[-0.916,-0.256],[-2.753,-0.139],[0,-0.589],[0,0],[0.611,0],[0,0],[0,0.611],[0,0],[-0.588,0.029],[-1.188,0.34],[-0.273,0.63],[0,4.414],[0,0],[0,0],[0,0],[-0.31,-0.714],[-1.284,-0.367],[-2.774,-0.137],[0,-0.589],[0,0],[0.61,0],[0,0],[0,0.611],[0,0],[-0.588,0.029],[-1.225,0.341],[-0.336,0.772],[0,4.414],[0,0],[0.312,0.719],[0.915,0.256],[2.744,0.139],[0,0.589],[0,0],[-0.611,0],[0,0],[0,-0.61],[0,0],[0.588,-0.029],[1.189,-0.34],[0.27,-0.626],[0,-4.424],[0,0],[0,0],[0,0],[0.312,0.719],[1.283,0.366],[2.764,0.137],[0,0.589],[0,0],[-0.61,0],[0,0],[0,-0.61],[0,0],[0.588,-0.03],[1.225,-0.342],[0.332,-0.767]],"o":[[0,0],[0,4.423],[0.334,0.774],[1.225,0.341],[0.588,0.03],[0,0],[0,0.611],[0,0],[-0.61,0],[0,0],[0,-0.589],[2.764,-0.138],[1.284,-0.366],[0.309,-0.713],[0,0],[0,0],[0,0],[0,4.423],[0.273,0.631],[1.189,0.34],[0.588,0.029],[0,0],[0,0.611],[0,0],[-0.611,0],[0,0],[0,-0.588],[2.744,-0.139],[0.914,-0.256],[0.308,-0.713],[0,0],[0,-4.417],[-0.333,-0.766],[-1.225,-0.341],[-0.588,-0.03],[0,0],[0,-0.61],[0,0],[0.61,0],[0,0],[0,0.589],[-2.774,0.137],[-1.284,0.367],[-0.313,0.719],[0,0],[0,0],[0,0],[0,-4.417],[-0.27,-0.623],[-1.189,-0.34],[-0.588,-0.029],[0,0],[0,-0.61],[0,0],[0.611,0],[0,0],[0,0.589],[-2.753,0.138],[-0.917,0.256],[-0.313,0.72]],"v":[[45.726,-54.451],[45.726,54.453],[46.557,61.448],[48.968,62.943],[60.261,63.818],[61.308,64.922],[61.308,74.557],[60.203,75.664],[12.337,75.664],[11.232,74.557],[11.232,64.922],[12.28,63.818],[23.588,62.948],[25.935,61.448],[26.766,54.453],[26.766,-19.508],[-26.817,-19.508],[-26.817,54.453],[-25.986,61.448],[-23.64,62.948],[-12.279,63.818],[-11.231,64.922],[-11.231,74.557],[-12.336,75.664],[-60.203,75.664],[-61.308,74.557],[-61.308,64.921],[-60.262,63.818],[-49.019,62.943],[-46.607,61.448],[-45.776,54.453],[-45.776,-54.451],[-46.61,-61.454],[-49.019,-62.943],[-60.262,-63.818],[-61.308,-64.921],[-61.308,-74.558],[-60.203,-75.663],[-12.336,-75.663],[-11.231,-74.558],[-11.231,-64.922],[-12.279,-63.818],[-23.64,-62.949],[-25.983,-61.453],[-26.817,-54.451],[-26.817,-33.81],[26.766,-33.81],[26.766,-54.451],[25.932,-61.454],[23.59,-62.948],[12.28,-63.818],[11.232,-64.922],[11.232,-74.558],[12.337,-75.663],[60.203,-75.663],[61.308,-74.558],[61.308,-64.921],[60.261,-63.818],[48.968,-62.943],[46.56,-61.454]],"c":true},"ix":2},"nm":"Path 1","mn":"ADBE Vector Shape - Group","hd":false},{"ty":"st","c":{"a":0,"k":[0,0,0,1],"ix":3},"o":{"a":0,"k":100,"ix":4},"w":{"a":0,"k":1,"ix":5},"lc":1,"lj":1,"ml":10,"bm":0,"nm":"Stroke 1","mn":"ADBE Vector Graphic - Stroke","hd":false},{"ty":"fl","c":{"a":0,"k":[0.101960791794,0.101960791794,0.101960791794,1],"ix":4},"o":{"a":0,"k":100,"ix":5},"r":1,"bm":0,"nm":"Fill 1","mn":"ADBE Vector Graphic - Fill","hd":false},{"ty":"tr","p":{"a":0,"k":[970.686,540.32],"ix":2},"a":{"a":0,"k":[0,0],"ix":1},"s":{"a":0,"k":[100,100],"ix":3},"r":{"a":0,"k":0,"ix":6},"o":{"a":0,"k":100,"ix":7},"sk":{"a":0,"k":0,"ix":4},"sa":{"a":0,"k":0,"ix":5},"nm":"Transform"}],"nm":"Group 1","np":3,"cix":2,"bm":0,"ix":1,"mn":"ADBE Vector Group","hd":false}],"ip":0,"op":1801.8018018018,"st":0,"bm":0},{"ddd":0,"ind":9,"ty":4,"nm":"Shape Layer 2","td":1,"sr":1,"ks":{"o":{"a":0,"k":100,"ix":11},"r":{"a":0,"k":0,"ix":10},"p":{"a":0,"k":[300,200,0],"ix":2},"a":{"a":0,"k":[0,0,0],"ix":1},"s":{"a":0,"k":[100,100,100],"ix":6}},"ao":0,"shapes":[{"ty":"gr","it":[{"ind":0,"ty":"sh","ix":1,"ks":{"a":0,"k":{"i":[[0,0],[0,0],[0,0],[0,0],[0,0],[0,0],[0,0],[0,0],[0,0],[0,0],[0,0],[0,0],[0,0],[0,0],[0,0],[0,0],[0,0],[0,0],[0,0],[0,0],[0,0],[0,0],[0,0],[0,0],[0,0],[0,0],[0,0],[0,0],[0,0],[0,0],[0,0],[0,0],[0,0],[0,0],[0,0],[0,0],[0,0],[0,0],[0,0],[0,0],[0,0]],"o":[[0,0],[0,0],[0,0],[0,0],[0,0],[0,0],[0,0],[0,0],[0,0],[0,0],[0,0],[0,0],[0,0],[0,0],[0,0],[0,0],[0,0],[0,0],[0,0],[0,0],[0,0],[0,0],[0,0],[0,0],[0,0],[0,0],[0,0],[0,0],[0,0],[0,0],[0,0],[0,0],[0,0],[0,0],[0,0],[0,0],[0,0],[0,0],[0,0],[0,0],[0,0]],"v":[[-56,-6],[-57,-18],[-59.513,-31.404],[-61.336,-41.125],[-62.853,-49.215],[-64.245,-56.642],[-64,-67.5],[-77.442,-67.788],[-84.488,-70.099],[-95.012,-70.902],[-103.013,-71.892],[-114.5,-68],[-121.604,-65.056],[-126.903,-60.33],[-131.5,-54],[-137.45,-46.65],[-140.05,-39.35],[-142.5,-31],[-144.85,-21.45],[-147.5,-10.5],[-147.917,1.823],[-146.167,12.899],[-143.487,24.542],[-139.598,37.575],[-135.084,43.722],[-132.153,49.743],[-126,56],[-119.396,62.648],[-112.357,67.013],[-104.508,68.527],[-98.064,69.217],[-89.5,69],[-80.2,66.1],[-72.5,61],[-68,54],[-62.528,44.849],[-58.566,35.481],[-55.604,24.613],[-55.066,17.981],[-55.698,10.943],[-54,5]],"c":false},"ix":2},"nm":"Path 1","mn":"ADBE Vector Shape - Group","hd":false},{"ty":"st","c":{"a":0,"k":[1,0,0,1],"ix":3},"o":{"a":0,"k":100,"ix":4},"w":{"a":0,"k":38,"ix":5},"lc":1,"lj":1,"ml":4,"bm":0,"nm":"Stroke 1","mn":"ADBE Vector Graphic - Stroke","hd":false},{"ty":"tr","p":{"a":0,"k":[0,0],"ix":2},"a":{"a":0,"k":[0,0],"ix":1},"s":{"a":0,"k":[100,100],"ix":3},"r":{"a":0,"k":0,"ix":6},"o":{"a":0,"k":100,"ix":7},"sk":{"a":0,"k":0,"ix":4},"sa":{"a":0,"k":0,"ix":5},"nm":"Transform"}],"nm":"Shape 1","np":3,"cix":2,"bm":0,"ix":1,"mn":"ADBE Vector Group","hd":false},{"ty":"tm","s":{"a":0,"k":0,"ix":1},"e":{"a":1,"k":[{"i":{"x":[0.833],"y":[0.833]},"o":{"x":[0.167],"y":[0.167]},"t":64,"s":[0]},{"t":78,"s":[100]}],"ix":2},"o":{"a":0,"k":0,"ix":3},"m":1,"ix":2,"nm":"Trim Paths 1","mn":"ADBE Vector Filter - Trim","hd":false}],"ip":0,"op":1801.8018018018,"st":0,"bm":0},{"ddd":0,"ind":10,"ty":4,"nm":"C","tt":1,"sr":1,"ks":{"o":{"a":0,"k":100,"ix":11},"r":{"a":0,"k":0,"ix":10},"p":{"a":0,"k":[300,200,0],"ix":2},"a":{"a":0,"k":[960,540,0],"ix":1},"s":{"a":0,"k":[100,100,100],"ix":6}},"ao":0,"shapes":[{"ty":"gr","it":[{"ind":0,"ty":"sh","ix":1,"ks":{"a":0,"k":{"i":[[0.067,-0.652],[0,0],[8.393,-11.259],[15.134,0],[8.581,7.001],[4.348,11.705],[0.524,1.704],[0,12.068],[-3.457,10.421],[-0.64,1.609],[-8.694,6.895],[-11.634,0],[-7.733,-7.125],[0,0],[-0.569,0],[0,0],[-0.032,-0.586],[0,0],[0.634,0],[0,0],[0.078,0.545],[8.015,9.278],[8.527,0],[5.796,-5.199],[3.169,-9.444],[0,-12.135],[-3.254,-9.749],[-5.905,-5.345],[-7.626,0],[-6.183,8.633],[-1.941,15.314],[0,0],[-0.557,0],[0,0]],"o":[[0,0],[-1.977,19.265],[-8.763,11.754],[-11.657,0],[-8.401,-6.849],[-0.611,-1.643],[-3.136,-10.187],[0,-12.372],[0.553,-1.666],[4.716,-11.863],[8.873,-7.036],[11.743,0],[0,0],[0.055,-0.567],[0,0],[0.587,0],[0,0],[0.035,0.633],[0,0],[-0.55,0],[-0.659,-4.585],[-5.322,-6.16],[-7.876,0],[-5.957,5.343],[-3.253,9.692],[0,12.141],[3.17,9.503],[5.734,5.192],[9.811,0],[6.505,-9.083],[0,0],[0.07,-0.552],[0,0],[0.655,0]],"v":[[54.018,10.696],[53.695,13.845],[38.068,59.847],[2.053,77.561],[-28.445,67.011],[-47.659,39.048],[-49.351,34.019],[-54.086,0.531],[-48.87,-33.77],[-47.091,-38.69],[-26.88,-66.958],[4.024,-77.562],[33.36,-66.826],[34.128,-74.793],[35.229,-75.792],[44.398,-75.792],[45.5,-74.748],[48.501,-20.02],[47.398,-18.854],[38.13,-18.854],[37.037,-19.797],[25.078,-53.793],[5.099,-63.436],[-15.218,-55.71],[-28.971,-33.426],[-33.873,-0.531],[-28.969,32.459],[-15.294,54.836],[4.561,62.552],[28.329,49.72],[41.057,12.952],[41.375,10.444],[42.471,9.478],[52.919,9.478]],"c":true},"ix":2},"nm":"Path 1","mn":"ADBE Vector Shape - Group","hd":false},{"ty":"st","c":{"a":0,"k":[0,0,0,1],"ix":3},"o":{"a":0,"k":100,"ix":4},"w":{"a":0,"k":1,"ix":5},"lc":1,"lj":1,"ml":10,"bm":0,"nm":"Stroke 1","mn":"ADBE Vector Graphic - Stroke","hd":false},{"ty":"fl","c":{"a":0,"k":[0.101960791794,0.101960791794,0.101960791794,1],"ix":4},"o":{"a":0,"k":100,"ix":5},"r":1,"bm":0,"nm":"Fill 1","mn":"ADBE Vector Graphic - Fill","hd":false},{"ty":"tr","p":{"a":0,"k":[858.874,540.341],"ix":2},"a":{"a":0,"k":[0,0],"ix":1},"s":{"a":0,"k":[100,100],"ix":3},"r":{"a":0,"k":0,"ix":6},"o":{"a":0,"k":100,"ix":7},"sk":{"a":0,"k":0,"ix":4},"sa":{"a":0,"k":0,"ix":5},"nm":"Transform"}],"nm":"Group 1","np":3,"cix":2,"bm":0,"ix":1,"mn":"ADBE Vector Group","hd":false}],"ip":0,"op":1801.8018018018,"st":0,"bm":0},{"ddd":0,"ind":11,"ty":4,"nm":"Shape Layer 1","td":1,"sr":1,"ks":{"o":{"a":1,"k":[{"i":{"x":[0.833],"y":[0.833]},"o":{"x":[0.167],"y":[0.167]},"t":0,"s":[0]},{"t":20.01953125,"s":[100]}],"ix":11},"r":{"a":0,"k":0,"ix":10},"p":{"a":1,"k":[{"i":{"x":0.833,"y":0.833},"o":{"x":0.167,"y":0.167},"t":6.006,"s":[504,200,0],"to":[-34.667,0,0],"ti":[34.667,0,0]},{"t":80.080078125,"s":[296,200,0]}],"ix":2},"a":{"a":0,"k":[0,0,0],"ix":1},"s":{"a":0,"k":[100,100,100],"ix":6}},"ao":0,"shapes":[{"ty":"gr","it":[{"ind":0,"ty":"sh","ix":1,"ks":{"a":0,"k":{"i":[[0,0],[0,0],[0,0],[0,0],[0,0],[0,0],[0,0],[0,0],[0,0],[0,0],[0,0],[0,0],[0,0],[0,0],[0,0],[0,0],[0,0]],"o":[[0,0],[0,0],[0,0],[0,0],[0,0],[0,0],[0,0],[0,0],[0,0],[0,0],[0,0],[0,0],[0,0],[0,0],[0,0],[0,0],[0,0]],"v":[[-204,-71],[-230,-63],[-248,-36],[-255,-17],[-258,4],[-253,23],[-245,47],[-235,61],[-219,72],[-202,73],[-184,64],[-172,47],[-162,27],[-159,-2],[-161,-30],[-169,-53],[-183,-65]],"c":true},"ix":2},"nm":"Path 1","mn":"ADBE Vector Shape - Group","hd":false},{"ty":"st","c":{"a":0,"k":[1,0,0,1],"ix":3},"o":{"a":0,"k":100,"ix":4},"w":{"a":0,"k":35,"ix":5},"lc":1,"lj":1,"ml":4,"bm":0,"nm":"Stroke 1","mn":"ADBE Vector Graphic - Stroke","hd":false},{"ty":"tr","p":{"a":0,"k":[0,0],"ix":2},"a":{"a":0,"k":[0,0],"ix":1},"s":{"a":0,"k":[100,100],"ix":3},"r":{"a":0,"k":0,"ix":6},"o":{"a":0,"k":100,"ix":7},"sk":{"a":0,"k":0,"ix":4},"sa":{"a":0,"k":0,"ix":5},"nm":"Transform"}],"nm":"Shape 1","np":3,"cix":2,"bm":0,"ix":1,"mn":"ADBE Vector Group","hd":false},{"ty":"tm","s":{"a":1,"k":[{"i":{"x":[0.552],"y":[0.283]},"o":{"x":[0.177],"y":[0.283]},"t":0,"s":[100]},{"i":{"x":[0.833],"y":[0.833]},"o":{"x":[0.167],"y":[0.167]},"t":16.016,"s":[73.684]},{"i":{"x":[0.833],"y":[0.833]},"o":{"x":[0.167],"y":[0.167]},"t":17.018,"s":[56.238]},{"i":{"x":[0.833],"y":[0.833]},"o":{"x":[0.167],"y":[0.167]},"t":18.018,"s":[42.922]},{"i":{"x":[0.833],"y":[0.833]},"o":{"x":[0.167],"y":[0.167]},"t":19.02,"s":[32.759]},{"i":{"x":[0.833],"y":[0.833]},"o":{"x":[0.167],"y":[0.167]},"t":20.02,"s":[25.003]},{"i":{"x":[0.833],"y":[0.833]},"o":{"x":[0.167],"y":[0.167]},"t":21.021,"s":[19.083]},{"i":{"x":[0.833],"y":[0.833]},"o":{"x":[0.167],"y":[0.167]},"t":22.021,"s":[14.564]},{"i":{"x":[0.833],"y":[0.833]},"o":{"x":[0.167],"y":[0.167]},"t":23.023,"s":[11.116]},{"i":{"x":[0.833],"y":[0.833]},"o":{"x":[0.167],"y":[0.167]},"t":24.023,"s":[8.484]},{"i":{"x":[0.833],"y":[0.833]},"o":{"x":[0.167],"y":[0.167]},"t":25.025,"s":[6.475]},{"i":{"x":[0.833],"y":[0.833]},"o":{"x":[0.167],"y":[0.167]},"t":26.025,"s":[4.942]},{"i":{"x":[0.833],"y":[0.833]},"o":{"x":[0.167],"y":[0.167]},"t":27.027,"s":[3.772]},{"i":{"x":[0.833],"y":[0.833]},"o":{"x":[0.167],"y":[0.167]},"t":28.027,"s":[2.879]},{"i":{"x":[0.833],"y":[0.833]},"o":{"x":[0.167],"y":[0.167]},"t":29.029,"s":[2.197]},{"i":{"x":[0.833],"y":[0.833]},"o":{"x":[0.167],"y":[0.167]},"t":30.029,"s":[1.677]},{"i":{"x":[0.833],"y":[0.833]},"o":{"x":[0.167],"y":[0.167]},"t":31.031,"s":[1.28]},{"i":{"x":[0.833],"y":[0.833]},"o":{"x":[0.167],"y":[0.167]},"t":32.031,"s":[0.977]},{"i":{"x":[0.833],"y":[0.833]},"o":{"x":[0.167],"y":[0.167]},"t":33.033,"s":[0.746]},{"i":{"x":[0.833],"y":[0.833]},"o":{"x":[0.167],"y":[0.167]},"t":34.033,"s":[0.569]},{"i":{"x":[0.833],"y":[0.833]},"o":{"x":[0.167],"y":[0.167]},"t":35.035,"s":[0.434]},{"i":{"x":[0.833],"y":[0.833]},"o":{"x":[0.167],"y":[0.167]},"t":36.035,"s":[0.331]},{"i":{"x":[0.833],"y":[0.833]},"o":{"x":[0.167],"y":[0.167]},"t":37.037,"s":[0.253]},{"i":{"x":[0.833],"y":[0.833]},"o":{"x":[0.167],"y":[0.167]},"t":38.037,"s":[0.193]},{"i":{"x":[0.833],"y":[0.833]},"o":{"x":[0.167],"y":[0.167]},"t":39.039,"s":[0.147]},{"i":{"x":[0.833],"y":[0.833]},"o":{"x":[0.167],"y":[0.167]},"t":40.041,"s":[0.112]},{"i":{"x":[0.833],"y":[0.833]},"o":{"x":[0.167],"y":[0.167]},"t":41.041,"s":[0.086]},{"i":{"x":[0.833],"y":[0.833]},"o":{"x":[0.167],"y":[0.167]},"t":42.043,"s":[0.066]},{"i":{"x":[0.833],"y":[0.833]},"o":{"x":[0.167],"y":[0.167]},"t":43.043,"s":[0.05]},{"i":{"x":[0.833],"y":[0.833]},"o":{"x":[0.167],"y":[0.167]},"t":44.045,"s":[0.038]},{"i":{"x":[0.833],"y":[0.833]},"o":{"x":[0.167],"y":[0.167]},"t":45.045,"s":[0.029]},{"i":{"x":[0.833],"y":[0.833]},"o":{"x":[0.167],"y":[0.167]},"t":46.047,"s":[0.022]},{"i":{"x":[0.833],"y":[0.833]},"o":{"x":[0.167],"y":[0.167]},"t":47.047,"s":[0.017]},{"i":{"x":[0.833],"y":[0.833]},"o":{"x":[0.167],"y":[0.167]},"t":48.049,"s":[0.013]},{"i":{"x":[0.833],"y":[0.833]},"o":{"x":[0.167],"y":[0.167]},"t":49.049,"s":[0.01]},{"i":{"x":[0.833],"y":[0.833]},"o":{"x":[0.167],"y":[0.167]},"t":50.051,"s":[0.008]},{"i":{"x":[0.833],"y":[0.833]},"o":{"x":[0.167],"y":[0.167]},"t":51.051,"s":[0.006]},{"i":{"x":[0.833],"y":[0.833]},"o":{"x":[0.167],"y":[0.167]},"t":52.053,"s":[0.004]},{"i":{"x":[0.833],"y":[0.833]},"o":{"x":[0.167],"y":[0.167]},"t":53.053,"s":[0.003]},{"i":{"x":[0.833],"y":[0.833]},"o":{"x":[0.167],"y":[0.167]},"t":54.055,"s":[0.003]},{"i":{"x":[0.833],"y":[0.833]},"o":{"x":[0.167],"y":[0.167]},"t":55.055,"s":[0.002]},{"i":{"x":[0.833],"y":[0.833]},"o":{"x":[0.167],"y":[0.167]},"t":56.057,"s":[0.001]},{"i":{"x":[0.833],"y":[0.833]},"o":{"x":[0.167],"y":[0.167]},"t":57.057,"s":[0.001]},{"i":{"x":[0.833],"y":[0.833]},"o":{"x":[0.167],"y":[0.167]},"t":58.059,"s":[0.001]},{"i":{"x":[0.833],"y":[0.833]},"o":{"x":[0.167],"y":[0.167]},"t":59.059,"s":[0.001]},{"i":{"x":[0.833],"y":[0.833]},"o":{"x":[0.167],"y":[0.167]},"t":60.061,"s":[0.001]},{"i":{"x":[0.833],"y":[0.833]},"o":{"x":[0.167],"y":[0.167]},"t":61.061,"s":[0]},{"i":{"x":[0.833],"y":[0.833]},"o":{"x":[0.167],"y":[0.167]},"t":62.062,"s":[0]},{"i":{"x":[0.833],"y":[0.833]},"o":{"x":[0.167],"y":[0.167]},"t":63.062,"s":[0]},{"i":{"x":[1],"y":[1]},"o":{"x":[0.167],"y":[0.167]},"t":64.064,"s":[0]},{"t":66.06640625,"s":[0]}],"ix":1},"e":{"a":0,"k":100,"ix":2},"o":{"a":0,"k":0,"ix":3},"m":1,"ix":2,"nm":"Trim Paths 1","mn":"ADBE Vector Filter - Trim","hd":false}],"ip":0,"op":1801.8018018018,"st":0,"bm":0},{"ddd":0,"ind":12,"ty":4,"nm":"O","tt":1,"sr":1,"ks":{"o":{"a":0,"k":100,"ix":11},"r":{"a":0,"k":0,"ix":10},"p":{"a":1,"k":[{"i":{"x":0.667,"y":1},"o":{"x":0.167,"y":0.167},"t":0,"s":[508,200,0],"to":[-34.667,0,0],"ti":[34.667,0,0]},{"t":36.03515625,"s":[300,200,0]}],"ix":2},"a":{"a":0,"k":[960,540,0],"ix":1},"s":{"a":0,"k":[100,100,100],"ix":6}},"ao":0,"shapes":[{"ty":"gr","it":[{"ind":0,"ty":"sh","ix":1,"ks":{"a":0,"k":{"i":[[1.524,-4.329],[0,0],[6.155,-2.556],[0,0],[6.292,2.175],[0,0],[2.325,5.817],[0,0],[-1.546,4.332],[0,0],[-6.056,2.558],[0,0],[-6.357,-2.211],[-2.329,-5.777],[0,0]],"o":[[0,0],[-1.999,5.679],[0,0],[-6.111,2.537],[0,0],[-6.572,-2.272],[0,0],[-1.712,-4.285],[0,0],[1.998,-5.598],[0,0],[6.159,-2.601],[6.527,2.272],[0,0],[1.722,4.272]],"v":[[42.225,-3.793],[29.283,46.57],[16.486,59.493],[11.081,61.738],[-8.37,62.306],[-8.492,62.264],[-22.503,49.526],[-35.559,16.851],[-35.814,3.584],[-17.883,-46.649],[-5.259,-59.433],[0,-61.654],[19.648,-62.266],[33.585,-49.599],[41.92,-17.035]],"c":true},"ix":2},"nm":"Path 1","mn":"ADBE Vector Shape - Group","hd":false},{"ind":1,"ty":"sh","ix":2,"ks":{"a":0,"k":{"i":[[-3.607,10.421],[0,0],[12.701,3.929],[0,0],[10.157,-3.199],[0,0],[4.919,-10.773],[0,0],[-6.774,-15.217],[0,0],[-12.794,-3.937],[0,0],[-10.11,3.165],[0,0],[-4.946,10.758],[0,0],[0,12.068]],"o":[[0,0],[-4.923,-10.931],[0,0],[-10.177,-3.148],[0,0],[-12.516,3.942],[0,0],[-6.923,15.162],[0,0],[4.906,11.021],[0,0],[10.128,3.117],[0,0],[12.518,-3.919],[0,0],[-3.272,-10.187],[0,-12.373]],"v":[[57.594,-33.7],[49.339,-52.028],[21.593,-75.421],[21.293,-75.514],[-10.097,-75.435],[-10.097,-75.434],[-37.511,-52.297],[-50.589,-23.656],[-50.821,23.723],[-38.255,51.947],[-10.37,75.511],[-10.262,75.544],[20.97,75.469],[21.261,75.378],[48.719,52.302],[57.092,34.089],[52.151,0.601]],"c":true},"ix":2},"nm":"Path 2","mn":"ADBE Vector Shape - Group","hd":false},{"ty":"st","c":{"a":0,"k":[0,0,0,1],"ix":3},"o":{"a":0,"k":100,"ix":4},"w":{"a":0,"k":1,"ix":5},"lc":1,"lj":1,"ml":10,"bm":0,"nm":"Stroke 1","mn":"ADBE Vector Graphic - Stroke","hd":false},{"ty":"fl","c":{"a":0,"k":[0.101960791794,0.101960791794,0.101960791794,1],"ix":4},"o":{"a":0,"k":100,"ix":5},"r":1,"bm":0,"nm":"Fill 1","mn":"ADBE Vector Graphic - Fill","hd":false},{"ty":"tr","p":{"a":0,"k":[749.193,540.271],"ix":2},"a":{"a":0,"k":[0,0],"ix":1},"s":{"a":0,"k":[100,100],"ix":3},"r":{"a":0,"k":0,"ix":6},"o":{"a":0,"k":100,"ix":7},"sk":{"a":0,"k":0,"ix":4},"sa":{"a":0,"k":0,"ix":5},"nm":"Transform"}],"nm":"Group 1","np":4,"cix":2,"bm":0,"ix":1,"mn":"ADBE Vector Group","hd":false}],"ip":0,"op":1801.8018018018,"st":0,"bm":0}],"markers":[]}